si4onnx/__init__.py
si4onnx/data.py
si4onnx/hypothesis.py
si4onnx/layers.py
si4onnx/nn.py
si4onnx/operators.py
si4onnx/si.py
si4onnx/utils.py
si4onnx-0.1.13.dist-info/METADATA
si4onnx-0.1.13.dist-info/WHEEL
si4onnx-0.1.13.dist-info/licenses/LICENSE
si4onnx-0.1.13.dist-info/RECORD
