Metadata-Version: 2.4
Name: si4onnx
Version: 0.1.13
Summary: A Package for Selective Inference in Deep Neural Networks
Project-URL: repository, https://github.com/Takeuchi-Lab-SI-Group/si4onnx
Author: Takeuchi Lab
Maintainer-email: Teruyuki Katsuoka <katsuoka.teruyuki.nagoyaml@gmail.com>
License: MIT
License-File: LICENSE
Requires-Python: >=3.10
Requires-Dist: numpy<2.0.0,>=1.26.4
Requires-Dist: onnx>=1.16.0
Requires-Dist: sicore>=2.3.0
Requires-Dist: torch>=2.2.0
